pyntrest/__init__.py
pyntrest/cli.py
pyntrest/api/__init__.py
pyntrest/api/server.py
pyntrest/client/__init__.py
pyntrest/client/pinterest.py
pyntrest/web/static/index.html
pyntrest/web/static/script.js
pyntrest/web/static/style.css
pyntrest-1.0.0.dist-info/licenses/LICENSE
pyntrest-1.0.0.dist-info/METADATA
pyntrest-1.0.0.dist-info/WHEEL
pyntrest-1.0.0.dist-info/entry_points.txt
pyntrest-1.0.0.dist-info/top_level.txt
pyntrest-1.0.0.dist-info/RECORD
