Metadata-Version: 2.4
Name: pyntrest
Version: 1.0.0
Summary: A Pinterest image search and download client
Home-page: https://github.com/redmoon0x/pynterest
Author: redmoon0x
Classifier: Programming Language :: Python :: 3
Classifier: License :: OSI Approved :: MIT License
Classifier: Operating System :: OS Independent
Requires-Python: >=3.7
License-File: LICENSE
Requires-Dist: requests>=2.31.0
Requires-Dist: fastapi>=0.104.1
Requires-Dist: uvicorn>=0.24.0
Requires-Dist: pydantic>=2.5.2
Requires-Dist: python-multipart>=0.0.6
Requires-Dist: aiohttp>=3.9.1
Requires-Dist: black>=23.11.0
Requires-Dist: pytest>=7.4.3
Dynamic: author
Dynamic: classifier
Dynamic: description
Dynamic: description-content-type
Dynamic: home-page
Dynamic: license-file
Dynamic: requires-dist
Dynamic: requires-python
Dynamic: summary
